cpgames/__init__.py
cpgames/cpgames.py
cpgames/core/__init__.py
cpgames/core/games/__init__.py
cpgames/core/games/aircraftwar/__init__.py
cpgames/core/games/aircraftwar/aircraftwar.py
cpgames/core/games/aircraftwar/modules/__init__.py
cpgames/core/games/aircraftwar/modules/interfaces.py
cpgames/core/games/aircraftwar/modules/sprites.py
cpgames/core/games/aircraftwar/resources/audios/Cool Space Music.mp3
cpgames/core/games/aircraftwar/resources/audios/boom.wav
cpgames/core/games/aircraftwar/resources/audios/shot.ogg
cpgames/core/games/aircraftwar/resources/images/asteroid.png
cpgames/core/games/aircraftwar/resources/images/bg_big.png
cpgames/core/games/aircraftwar/resources/images/bullet.png
cpgames/core/games/aircraftwar/resources/images/seamless_space.png
cpgames/core/games/aircraftwar/resources/images/ship.png
cpgames/core/games/aircraftwar/resources/images/ship_exploded.png
cpgames/core/games/aircraftwar/resources/images/space3.jpg
cpgames/core/games/alieninvasion/__init__.py
cpgames/core/games/alieninvasion/alieninvasion.py
cpgames/core/games/alieninvasion/modules/__init__.py
cpgames/core/games/alieninvasion/modules/sprites.py
cpgames/core/games/alieninvasion/modules/utils.py
cpgames/core/games/alieninvasion/resources/bgm.mp3
cpgames/core/games/angrybirds/__init__.py
cpgames/core/games/angrybirds/angrybirds.py
cpgames/core/games/angrybirds/modules/__init__.py
cpgames/core/games/angrybirds/modules/gamelevels.py
cpgames/core/games/angrybirds/modules/misc.py
cpgames/core/games/angrybirds/modules/sprites.py
cpgames/core/games/angrybirds/resources/audios/bgm.ogg
cpgames/core/games/angrybirds/resources/fonts/Comic_Kings.ttf
cpgames/core/games/angrybirds/resources/fonts/arfmoochikncheez.ttf
cpgames/core/games/angrybirds/resources/images/bird.png
cpgames/core/games/angrybirds/resources/images/block.png
cpgames/core/games/angrybirds/resources/images/block_destroyed.png
cpgames/core/games/angrybirds/resources/images/pig_1.png
cpgames-0.1.2.dist-info/LICENSE
cpgames-0.1.2.dist-info/METADATA
cpgames-0.1.2.dist-info/WHEEL
cpgames-0.1.2.dist-info/top_level.txt
cpgames-0.1.2.dist-info/zip-safe
cpgames-0.1.2.dist-info/RECORD
