Metadata-Version: 2.1
Name: cpgames
Version: 0.1.2
Summary: Games: Create interesting games by pure python
Home-page: https://github.com/CharlesPikachu/Games
Author: Zhenchao Jin
Author-email: charlesblwx@gmail.com
License: Apache License 2.0
Platform: UNKNOWN
Classifier: License :: OSI Approved :: Apache Software License
Classifier: Programming Language :: Python :: 3
Classifier: Intended Audience :: Developers
Classifier: Operating System :: OS Independent
License-File: LICENSE
